flake8-start.py
examples/duplicate.py
examples/unused_duplicate.py
flake8_start-0.0.1.dist-info/METADATA
flake8_start-0.0.1.dist-info/WHEEL
flake8_start-0.0.1.dist-info/licenses/LICENSE
flake8_start-0.0.1.dist-info/RECORD
