Metadata-Version: 2.1
Name: flake8-start
Version: 0.0.1
Summary: A command line tool to create flake8 configuration file
Project-URL: Homepage, https://github.com/szabgab/flake8-start
Project-URL: Bug Tracker, https://github.com/szabgab/flake8-start/issues
Author-email: Gabor Szabo <gabor@szabgab.com>
License-File: LICENSE
Classifier: License :: OSI Approved :: MIT License
Classifier: Operating System :: OS Independent
Classifier: Programming Language :: Python :: 3
Requires-Python: >=3.7
